{
 "commands": [
  {
   "params": {
    "to_port": 100021, 
    "from_port": 150021
   }, 
   "jsonrpc": "2.0", 
   "id": 0, 
   "method": "add_link"
  }, 
  {
   "params": {
    "hs": {
     "diff": [
      []
     ], 
     "list": [
      "xxxxxxxx,xxxxxxxx,xxxxxxxx,xxxxxxxx,xxxxxxxx,xxxxxxxx,xxxxxxxx,xxxxxxxx,xxxxxxxx,xxxxxxxx,xxxxxxxx,xxxxxxxx,xxxxxxxx,xxxxxxxx,xxxxxxxx,xxxxxxxx"
     ]
    }, 
    "ports": [
     150021
    ]
   }, 
   "jsonrpc": "2.0", 
   "id": 1, 
   "method": "add_source"
  },


  

  {
   "params": {
    "to_port": 200010, 
    "from_port": 250010
   }, 
   "jsonrpc": "2.0", 
   "id": 1, 
   "method": "add_link"
  }, 
  {
   "params": {
    "hs": {
     "diff": [
      []
     ], 
     "list": [
      "xxxxxxxx,xxxxxxxx,xxxxxxxx,xxxxxxxx,xxxxxxxx,xxxxxxxx,xxxxxxxx,xxxxxxxx,xxxxxxxx,xxxxxxxx,xxxxxxxx,xxxxxxxx,xxxxxxxx,xxxxxxxx,xxxxxxxx,xxxxxxxx"
     ]
    }, 
    "ports": [
     250010
    ]
   }, 
   "jsonrpc": "2.0", 
   "id": 2, 
   "method": "add_source"
  }, 
  {
   "params": {
    "to_port": 300003, 
    "from_port": 350003
   }, 
   "jsonrpc": "2.0", 
   "id": 2, 
   "method": "add_link"
  }, 
  {
   "params": {
    "hs": {
     "diff": [
      []
     ], 
     "list": [
      "xxxxxxxx,xxxxxxxx,xxxxxxxx,xxxxxxxx,xxxxxxxx,xxxxxxxx,xxxxxxxx,xxxxxxxx,xxxxxxxx,xxxxxxxx,xxxxxxxx,xxxxxxxx,xxxxxxxx,xxxxxxxx,xxxxxxxx,xxxxxxxx"
     ]
    }, 
    "ports": [
     350003
    ]
   }, 
   "jsonrpc": "2.0", 
   "id": 3, 
   "method": "add_source"
  },
  {
   "params": {
    "to_port": 400002, 
    "from_port": 450002
   }, 
   "jsonrpc": "2.0", 
   "id": 3, 
   "method": "add_link"
  }, 
  {
   "params": {
    "hs": {
     "diff": [
      []
     ], 
     "list": [
      "xxxxxxxx,xxxxxxxx,xxxxxxxx,xxxxxxxx,xxxxxxxx,xxxxxxxx,xxxxxxxx,xxxxxxxx,xxxxxxxx,xxxxxxxx,xxxxxxxx,xxxxxxxx,xxxxxxxx,xxxxxxxx,xxxxxxxx,xxxxxxxx"
     ]
    }, 
    "ports": [
     450002
    ]
   }, 
   "jsonrpc": "2.0", 
   "id": 4, 
   "method": "add_source"
  }, 
  {
   "params": {
    "to_port": 500003, 
    "from_port": 550003
   }, 
   "jsonrpc": "2.0", 
   "id": 4, 
   "method": "add_link"
  }, 
  {
   "params": {
    "hs": {
     "diff": [
      []
     ], 
     "list": [
      "xxxxxxxx,xxxxxxxx,xxxxxxxx,xxxxxxxx,xxxxxxxx,xxxxxxxx,xxxxxxxx,xxxxxxxx,xxxxxxxx,xxxxxxxx,xxxxxxxx,xxxxxxxx,xxxxxxxx,xxxxxxxx,xxxxxxxx,xxxxxxxx"
     ]
    }, 
    "ports": [
     550003
    ]
   }, 
   "jsonrpc": "2.0", 
   "id": 5, 
   "method": "add_source"
  },
  {
   "params": {
    "to_port": 600002, 
    "from_port": 650002
   }, 
   "jsonrpc": "2.0", 
   "id": 5, 
   "method": "add_link"
  }, 
  {
   "params": {
    "hs": {
     "diff": [
      []
     ], 
     "list": [
      "xxxxxxxx,xxxxxxxx,xxxxxxxx,xxxxxxxx,xxxxxxxx,xxxxxxxx,xxxxxxxx,xxxxxxxx,xxxxxxxx,xxxxxxxx,xxxxxxxx,xxxxxxxx,xxxxxxxx,xxxxxxxx,xxxxxxxx,xxxxxxxx"
     ]
    }, 
    "ports": [
     650002
    ]
   }, 
   "jsonrpc": "2.0", 
   "id": 6, 
   "method": "add_source"
  }, 
  {
   "params": {
    "to_port": 700003, 
    "from_port": 750003
   }, 
   "jsonrpc": "2.0", 
   "id": 6, 
   "method": "add_link"
  }, 
  {
   "params": {
    "hs": {
     "diff": [
      []
     ], 
     "list": [
      "xxxxxxxx,xxxxxxxx,xxxxxxxx,xxxxxxxx,xxxxxxxx,xxxxxxxx,xxxxxxxx,xxxxxxxx,xxxxxxxx,xxxxxxxx,xxxxxxxx,xxxxxxxx,xxxxxxxx,xxxxxxxx,xxxxxxxx,xxxxxxxx"
     ]
    }, 
    "ports": [
     750003
    ]
   }, 
   "jsonrpc": "2.0", 
   "id": 7, 
   "method": "add_source"
  }, 
  {
   "params": {
    "to_port": 800002, 
    "from_port": 850002
   }, 
   "jsonrpc": "2.0", 
   "id": 7, 
   "method": "add_link"
  }, 
  {
   "params": {
    "hs": {
     "diff": [
      []
     ], 
     "list": [
      "xxxxxxxx,xxxxxxxx,xxxxxxxx,xxxxxxxx,xxxxxxxx,xxxxxxxx,xxxxxxxx,xxxxxxxx,xxxxxxxx,xxxxxxxx,xxxxxxxx,xxxxxxxx,xxxxxxxx,xxxxxxxx,xxxxxxxx,xxxxxxxx"
     ]
    }, 
    "ports": [
     850002
    ]
   }, 
   "jsonrpc": "2.0", 
   "id": 8, 
   "method": "add_source"
  }, 
  {
   "params": {
    "to_port": 900003, 
    "from_port": 950003
   }, 
   "jsonrpc": "2.0", 
   "id": 8, 
   "method": "add_link"
  },
  {
   "params": {
    "hs": {
     "diff": [
      []
     ], 
     "list": [
      "xxxxxxxx,xxxxxxxx,xxxxxxxx,xxxxxxxx,xxxxxxxx,xxxxxxxx,xxxxxxxx,xxxxxxxx,xxxxxxxx,xxxxxxxx,xxxxxxxx,xxxxxxxx,xxxxxxxx,xxxxxxxx,xxxxxxxx,xxxxxxxx"
     ]
    }, 
    "ports": [
     950003
    ]
   }, 
   "jsonrpc": "2.0", 
   "id": 9, 
   "method": "add_source"
  }, 
  {
   "params": {
    "to_port": 1000003, 
    "from_port": 1050003
   }, 
   "jsonrpc": "2.0", 
   "id": 9, 
   "method": "add_link"
  }, 
  {
   "params": {
    "hs": {
     "diff": [
      []
     ], 
     "list": [
      "xxxxxxxx,xxxxxxxx,xxxxxxxx,xxxxxxxx,xxxxxxxx,xxxxxxxx,xxxxxxxx,xxxxxxxx,xxxxxxxx,xxxxxxxx,xxxxxxxx,xxxxxxxx,xxxxxxxx,xxxxxxxx,xxxxxxxx,xxxxxxxx"
     ]
    }, 
    "ports": [
     1050003
    ]
   }, 
   "jsonrpc": "2.0", 
   "id": 10, 
   "method": "add_source"
  },
  {
   "params": {
    "to_port": 1100003, 
    "from_port": 1150003
   }, 
   "jsonrpc": "2.0", 
   "id": 10, 
   "method": "add_link"
  }, 
  {
   "params": {
    "hs": {
     "diff": [
      []
     ], 
     "list": [
      "xxxxxxxx,xxxxxxxx,xxxxxxxx,xxxxxxxx,xxxxxxxx,xxxxxxxx,xxxxxxxx,xxxxxxxx,xxxxxxxx,xxxxxxxx,xxxxxxxx,xxxxxxxx,xxxxxxxx,xxxxxxxx,xxxxxxxx,xxxxxxxx"
     ]
    }, 
    "ports": [
     1150003
    ]
   }, 
   "jsonrpc": "2.0", 
   "id": 11, 
   "method": "add_source"
  },
  {
   "params": {
    "to_port": 1200002, 
    "from_port": 1250002
   }, 
   "jsonrpc": "2.0", 
   "id": 11, 
   "method": "add_link"
  }, 
  {
   "params": {
    "hs": {
     "diff": [
      []
     ], 
     "list": [
      "xxxxxxxx,xxxxxxxx,xxxxxxxx,xxxxxxxx,xxxxxxxx,xxxxxxxx,xxxxxxxx,xxxxxxxx,xxxxxxxx,xxxxxxxx,xxxxxxxx,xxxxxxxx,xxxxxxxx,xxxxxxxx,xxxxxxxx,xxxxxxxx"
     ]
    }, 
    "ports": [
     1250002
    ]
   }, 
   "jsonrpc": "2.0", 
   "id": 12, 
   "method": "add_source"
  }, 
  {
   "params": {
    "to_port": 1300002, 
    "from_port": 1350002
   }, 
   "jsonrpc": "2.0", 
   "id": 12, 
   "method": "add_link"
  }, 
  {
   "params": {
    "hs": {
     "diff": [
      []
     ], 
     "list": [
      "xxxxxxxx,xxxxxxxx,xxxxxxxx,xxxxxxxx,xxxxxxxx,xxxxxxxx,xxxxxxxx,xxxxxxxx,xxxxxxxx,xxxxxxxx,xxxxxxxx,xxxxxxxx,xxxxxxxx,xxxxxxxx,xxxxxxxx,xxxxxxxx"
     ]
    }, 
    "ports": [
     1350002
    ]
   }, 
   "jsonrpc": "2.0", 
   "id": 13, 
   "method": "add_source"
  }, 
  {
   "params": {
    "to_port": 1400002, 
    "from_port": 1450002
   }, 
   "jsonrpc": "2.0", 
   "id": 13, 
   "method": "add_link"
  }, 
  {
   "params": {
    "hs": {
     "diff": [
      []
     ], 
     "list": [
      "xxxxxxxx,xxxxxxxx,xxxxxxxx,xxxxxxxx,xxxxxxxx,xxxxxxxx,xxxxxxxx,xxxxxxxx,xxxxxxxx,xxxxxxxx,xxxxxxxx,xxxxxxxx,xxxxxxxx,xxxxxxxx,xxxxxxxx,xxxxxxxx"
     ]
    }, 
    "ports": [
     1450002
    ]
   }, 
   "jsonrpc": "2.0", 
   "id": 14, 
   "method": "add_source"
  }, 
  {
   "params": {
    "to_port": 1500004, 
    "from_port": 1550004
   }, 
   "jsonrpc": "2.0", 
   "id": 14, 
   "method": "add_link"
  }, 
  {
   "params": {
    "hs": {
     "diff": [
      []
     ], 
     "list": [
      "xxxxxxxx,xxxxxxxx,xxxxxxxx,xxxxxxxx,xxxxxxxx,xxxxxxxx,xxxxxxxx,xxxxxxxx,xxxxxxxx,xxxxxxxx,xxxxxxxx,xxxxxxxx,xxxxxxxx,xxxxxxxx,xxxxxxxx,xxxxxxxx"
     ]
    }, 
    "ports": [
     1550004
    ]
   }, 
   "jsonrpc": "2.0", 
   "id": 15, 
   "method": "add_source"
  }, 
  {
   "params": {
    "to_port": 1600003, 
    "from_port": 1650003
   }, 
   "jsonrpc": "2.0", 
   "id": 15, 
   "method": "add_link"
  }, 
  {
   "params": {
    "hs": {
     "diff": [
      []
     ], 
     "list": [
      "xxxxxxxx,xxxxxxxx,xxxxxxxx,xxxxxxxx,xxxxxxxx,xxxxxxxx,xxxxxxxx,xxxxxxxx,xxxxxxxx,xxxxxxxx,xxxxxxxx,xxxxxxxx,xxxxxxxx,xxxxxxxx,xxxxxxxx,xxxxxxxx"
     ]
    }, 
    "ports": [
     1650003
    ]
   }, 
   "jsonrpc": "2.0", 
   "id": 16, 
   "method": "add_source"
  },

  {
   "params": {
    "to_port": 400007, 
    "from_port": 320007
   }, 
   "jsonrpc": "2.0", 
   "id": 2, 
   "method": "remove_link"
  },
  {
   "params": {
    "to_port": 400007, 
    "from_port": 320007
   }, 
   "jsonrpc": "2.0", 
   "id": 3, 
   "method": "add_link"
  },
  {
   "params": {
    "to_port": 600010, 
    "from_port": 520012
   }, 
   "jsonrpc": "2.0", 
   "id": 2, 
   "method": "remove_link"
  },
  {
   "params": {
    "to_port": 600010, 
    "from_port": 520012
   }, 
   "jsonrpc": "2.0", 
   "id": 3, 
   "method": "add_link"
  },
  {
   "params": {
    "to_port": 100025, 
    "from_port": 720006
   }, 
   "jsonrpc": "2.0", 
   "id": 2, 
   "method": "remove_link"
  },
  {
   "params": {
    "to_port": 100025, 
    "from_port": 720006
   }, 
   "jsonrpc": "2.0", 
   "id": 3, 
   "method": "add_link"
  },
  {
   "params": {
    "to_port": 400001, 
    "from_port": 120003
   }, 
   "jsonrpc": "2.0", 
   "id": 2, 
   "method": "remove_link"
  },
  {
   "params": {
    "to_port": 400001, 
    "from_port": 120003
   }, 
   "jsonrpc": "2.0", 
   "id": 3, 
   "method": "add_link"
  },
  {
   "params": {
    "to_port": 900001, 
    "from_port": 220013
   }, 
   "jsonrpc": "2.0", 
   "id": 2, 
   "method": "remove_link"
  },
  {
   "params": {
    "to_port": 900001, 
    "from_port": 220013
   }, 
   "jsonrpc": "2.0", 
   "id": 3, 
   "method": "add_link"
  },
  {
   "params": {
    "to_port": 400007, 
    "from_port": 320007
   }, 
   "jsonrpc": "2.0", 
   "id": 2, 
   "method": "remove_link"
  },
  {
   "params": {
    "to_port": 400007, 
    "from_port": 320007
   }, 
   "jsonrpc": "2.0", 
   "id": 3, 
   "method": "add_link"
  },
  {
   "params": {
    "to_port": 600010, 
    "from_port": 520012
   }, 
   "jsonrpc": "2.0", 
   "id": 2, 
   "method": "remove_link"
  },
  {
   "params": {
    "to_port": 600010, 
    "from_port": 520012
   }, 
   "jsonrpc": "2.0", 
   "id": 3, 
   "method": "add_link"
  },
  {
   "params": {
    "to_port": 700007, 
    "from_port": 820007
   }, 
   "jsonrpc": "2.0", 
   "id": 2, 
   "method": "remove_link"
  },
  {
   "params": {
    "to_port": 700007, 
    "from_port": 820007
   }, 
   "jsonrpc": "2.0", 
   "id": 3, 
   "method": "add_link"
  },
  {
   "params": {
    "to_port": 1000008, 
    "from_port": 920008
   }, 
   "jsonrpc": "2.0", 
   "id": 2, 
   "method": "remove_link"
  },
  {
   "params": {
    "to_port": 1000008, 
    "from_port": 920008
   }, 
   "jsonrpc": "2.0", 
   "id": 3, 
   "method": "add_link"
  },

  {
   "params": {
    "table": 10, 
    "id": 12
   }, 
   "jsonrpc": "2.0", 
   "id": 11, 
   "method": "re_add_rule"
  },
  {
   "params": {
    "table": 11, 
    "id": 55
   }, 
   "11": "2.0", 
   "id": 11, 
   "method": "re_add_rule"
  },
  {
   "params": {
    "table": 12, 
    "id": 9
   }, 
   "11": "2.0", 
   "id": 11, 
   "method": "re_add_rule"
  },
  {
   "params": {
    "table": 20, 
    "id": 5
   }, 
   "jsonrpc": "2.0", 
   "id": 11, 
   "method": "re_add_rule"
  },
  {
   "params": {
    "table": 21, 
    "id": 320
   }, 
   "11": "2.0", 
   "id": 11, 
   "method": "re_add_rule"
  },
  {
   "params": {
    "table": 22, 
    "id": 10
   }, 
   "11": "2.0", 
   "id": 11, 
   "method": "re_add_rule"
  },
  {
   "params": {
    "table": 30, 
    "id": 5
   }, 
   "jsonrpc": "2.0", 
   "id": 11, 
   "method": "re_add_rule"
  },
  {
   "params": {
    "table": 31, 
    "id": 35
   }, 
   "11": "2.0", 
   "id": 11, 
   "method": "re_add_rule"
  },
  {
   "params": {
    "table": 32, 
    "id": 30
   }, 
   "11": "2.0", 
   "id": 11, 
   "method": "re_add_rule"
  },
  {
   "params": {
    "table": 40, 
    "id": 15
   }, 
   "jsonrpc": "2.0", 
   "id": 11, 
   "method": "re_add_rule"
  },
  {
   "params": {
    "table": 41, 
    "id": 18
   }, 
   "11": "2.0", 
   "id": 11, 
   "method": "re_add_rule"
  },
  {
   "params": {
    "table": 42, 
    "id": 25
   }, 
   "11": "2.0", 
   "id": 11, 
   "method": "re_add_rule"
  },
  {
   "params": {
    "table": 70, 
    "id": 20
   }, 
   "jsonrpc": "2.0", 
   "id": 11, 
   "method": "re_add_rule"
  },
  {
   "params": {
    "table": 71, 
    "id": 22
   }, 
   "11": "2.0", 
   "id": 11, 
   "method": "re_add_rule"
  },
  {
   "params": {
    "table": 72, 
    "id": 15
   }, 
   "11": "2.0", 
   "id": 11, 
   "method": "re_add_rule"
  },
  {
   "params": {
    "table": 160, 
    "id": 32
   }, 
   "jsonrpc": "2.0", 
   "id": 11, 
   "method": "re_add_rule"
  },
  {
   "params": {
    "table": 161, 
    "id": 55
   }, 
   "11": "2.0", 
   "id": 11, 
   "method": "re_add_rule"
  },
  {
   "params": {
    "table": 162, 
    "id": 15
   }, 
   "11": "2.0", 
   "id": 11, 
   "method": "re_add_rule"
  }


 ]
}