{
 "commands": [
  {
   "params": {
    "to_port": 100001,
    "from_port": 150001
   }, 
   "jsonrpc": "2.0", 
   "id": 0, 
   "method": "add_link"
  }, 
  {
   "params": {
    "hs": {
     "diff": [
      []
     ], 
     "list": [
      "xxxxxxxx,xxxxxxxx,xxxxxxxx,xxxxxxxx,xxxxxxxx,xxxxxxxx"
     ]
    }, 
    "ports": [
     150001
    ]
   }, 
   "jsonrpc": "2.0", 
   "id": 1, 
   "method": "add_source"
  },

  {
   "params": {
    "to_port": 100004, 
    "from_port": 150004
   }, 
   "jsonrpc": "2.0", 
   "id": 1, 
   "method": "add_link"
  }, 
  {
   "params": {
    "hs": {
     "diff": [
      []
     ], 
     "list": [
      "xxxxxxxx,xxxxxxxx,xxxxxxxx,xxxxxxxx,xxxxxxxx,xxxxxxxx"
     ]
    }, 
    "ports": [
     150004
    ]
   }, 
   "jsonrpc": "2.0", 
   "id": 2, 
   "method": "add_source"
  }, 
  {
   "params": {
    "to_port": 100007, 
    "from_port": 150007
   }, 
   "jsonrpc": "2.0", 
   "id": 2, 
   "method": "add_link"
  }, 
  {
   "params": {
    "hs": {
     "diff": [
      []
     ], 
     "list": [
      "xxxxxxxx,xxxxxxxx,xxxxxxxx,xxxxxxxx,xxxxxxxx,xxxxxxxx"
     ]
    }, 
    "ports": [
     150007
    ]
   }, 
   "jsonrpc": "2.0", 
   "id": 3, 
   "method": "add_source"
  },
  {
   "params": {
    "to_port": 100008, 
    "from_port": 150008
   }, 
   "jsonrpc": "2.0", 
   "id": 3, 
   "method": "add_link"
  }, 
  {
   "params": {
    "hs": {
     "diff": [
      []
     ], 
     "list": [
      "xxxxxxxx,xxxxxxxx,xxxxxxxx,xxxxxxxx,xxxxxxxx,xxxxxxxx"
     ]
    }, 
    "ports": [
     150008
    ]
   }, 
   "jsonrpc": "2.0", 
   "id": 4, 
   "method": "add_source"
  }, 
  {
   "params": {
    "to_port": 100009, 
    "from_port": 150009
   }, 
   "jsonrpc": "2.0", 
   "id": 4, 
   "method": "add_link"
  }, 
  {
   "params": {
    "hs": {
     "diff": [
      []
     ], 
     "list": [
      "xxxxxxxx,xxxxxxxx,xxxxxxxx,xxxxxxxx,xxxxxxxx,xxxxxxxx"
     ]
    }, 
    "ports": [
     150009
    ]
   }, 
   "jsonrpc": "2.0", 
   "id": 5, 
   "method": "add_source"
  },
  {
   "params": {
    "to_port": 100010, 
    "from_port": 150010
   }, 
   "jsonrpc": "2.0", 
   "id": 5, 
   "method": "add_link"
  }, 
  {
   "params": {
    "hs": {
     "diff": [
      []
     ], 
     "list": [
      "xxxxxxxx,xxxxxxxx,xxxxxxxx,xxxxxxxx,xxxxxxxx,xxxxxxxx"
     ]
    }, 
    "ports": [
     150010
    ]
   }, 
   "jsonrpc": "2.0", 
   "id": 6, 
   "method": "add_source"
  }, 
  {
   "params": {
    "to_port": 100015, 
    "from_port": 150015
   }, 
   "jsonrpc": "2.0", 
   "id": 6, 
   "method": "add_link"
  }, 
  {
   "params": {
    "hs": {
     "diff": [
      []
     ], 
     "list": [
      "xxxxxxxx,xxxxxxxx,xxxxxxxx,xxxxxxxx,xxxxxxxx,xxxxxxxx"
     ]
    }, 
    "ports": [
     150015
    ]
   }, 
   "jsonrpc": "2.0", 
   "id": 7, 
   "method": "add_source"
  }, 
  {
   "params": {
    "to_port": 100017, 
    "from_port": 150017
   }, 
   "jsonrpc": "2.0", 
   "id": 7, 
   "method": "add_link"
  }, 
  {
   "params": {
    "hs": {
     "diff": [
      []
     ], 
     "list": [
      "xxxxxxxx,xxxxxxxx,xxxxxxxx,xxxxxxxx,xxxxxxxx,xxxxxxxx"
     ]
    }, 
    "ports": [
     150017
    ]
   }, 
   "jsonrpc": "2.0", 
   "id": 8, 
   "method": "add_source"
  }, 
  {
   "params": {
    "to_port": 100018, 
    "from_port": 150018
   }, 
   "jsonrpc": "2.0", 
   "id": 8, 
   "method": "add_link"
  },
  {
   "params": {
    "hs": {
     "diff": [
      []
     ], 
     "list": [
      "xxxxxxxx,xxxxxxxx,xxxxxxxx,xxxxxxxx,xxxxxxxx,xxxxxxxx"
     ]
    }, 
    "ports": [
     150018
    ]
   }, 
   "jsonrpc": "2.0", 
   "id": 9, 
   "method": "add_source"
  },
  {
   "params": {
    "to_port": 100019, 
    "from_port": 150019
   }, 
   "jsonrpc": "2.0", 
   "id": 8, 
   "method": "add_link"
  },
  {
   "params": {
    "hs": {
     "diff": [
      []
     ], 
     "list": [
      "xxxxxxxx,xxxxxxxx,xxxxxxxx,xxxxxxxx,xxxxxxxx,xxxxxxxx"
     ]
    }, 
    "ports": [
     150019
    ]
   }, 
   "jsonrpc": "2.0", 
   "id": 9, 
   "method": "add_source"
  },
  {
   "params": {
    "to_port": 100020, 
    "from_port": 150020
   }, 
   "jsonrpc": "2.0", 
   "id": 8, 
   "method": "add_link"
  },
  {
   "params": {
    "hs": {
     "diff": [
      []
     ], 
     "list": [
      "xxxxxxxx,xxxxxxxx,xxxxxxxx,xxxxxxxx,xxxxxxxx,xxxxxxxx"
     ]
    }, 
    "ports": [
     150020
    ]
   }, 
   "jsonrpc": "2.0", 
   "id": 9, 
   "method": "add_source"
  },
  {
   "params": {
    "to_port": 100021, 
    "from_port": 150021
   }, 
   "jsonrpc": "2.0", 
   "id": 8, 
   "method": "add_link"
  },
  {
   "params": {
    "hs": {
     "diff": [
      []
     ], 
     "list": [
      "xxxxxxxx,xxxxxxxx,xxxxxxxx,xxxxxxxx,xxxxxxxx,xxxxxxxx"
     ]
    }, 
    "ports": [
     150021
    ]
   }, 
   "jsonrpc": "2.0", 
   "id": 9, 
   "method": "add_source"
  },
  {
   "params": {
    "to_port": 100022, 
    "from_port": 150022
   }, 
   "jsonrpc": "2.0", 
   "id": 8, 
   "method": "add_link"
  },
  {
   "params": {
    "hs": {
     "diff": [
      []
     ], 
     "list": [
      "xxxxxxxx,xxxxxxxx,xxxxxxxx,xxxxxxxx,xxxxxxxx,xxxxxxxx"
     ]
    }, 
    "ports": [
     150022
    ]
   }, 
   "jsonrpc": "2.0", 
   "id": 9, 
   "method": "add_source"
  },
  {
   "params": {
    "to_port": 100023, 
    "from_port": 150023
   }, 
   "jsonrpc": "2.0", 
   "id": 8, 
   "method": "add_link"
  },
  {
   "params": {
    "hs": {
     "diff": [
      []
     ], 
     "list": [
      "xxxxxxxx,xxxxxxxx,xxxxxxxx,xxxxxxxx,xxxxxxxx,xxxxxxxx"
     ]
    }, 
    "ports": [
     150023
    ]
   }, 
   "jsonrpc": "2.0", 
   "id": 9, 
   "method": "add_source"
  },
  {
   "params": {
    "to_port": 100024, 
    "from_port": 150024
   }, 
   "jsonrpc": "2.0", 
   "id": 8, 
   "method": "add_link"
  },
  {
   "params": {
    "hs": {
     "diff": [
      []
     ], 
     "list": [
      "xxxxxxxx,xxxxxxxx,xxxxxxxx,xxxxxxxx,xxxxxxxx,xxxxxxxx"
     ]
    }, 
    "ports": [
     150024
    ]
   }, 
   "jsonrpc": "2.0", 
   "id": 9, 
   "method": "add_source"
  },
  {
   "params": {
    "to_port": 100025, 
    "from_port": 150025
   }, 
   "jsonrpc": "2.0", 
   "id": 8, 
   "method": "add_link"
  },
  {
   "params": {
    "hs": {
     "diff": [
      []
     ], 
     "list": [
      "xxxxxxxx,xxxxxxxx,xxxxxxxx,xxxxxxxx,xxxxxxxx,xxxxxxxx"
     ]
    }, 
    "ports": [
     150025
    ]
   }, 
   "jsonrpc": "2.0", 
   "id": 9, 
   "method": "add_source"
  },
  {
   "params": {
    "to_port": 100026, 
    "from_port": 150026
   }, 
   "jsonrpc": "2.0", 
   "id": 8, 
   "method": "add_link"
  },
  {
   "params": {
    "hs": {
     "diff": [
      []
     ], 
     "list": [
      "xxxxxxxx,xxxxxxxx,xxxxxxxx,xxxxxxxx,xxxxxxxx,xxxxxxxx"
     ]
    }, 
    "ports": [
     150026
    ]
   }, 
   "jsonrpc": "2.0", 
   "id": 9, 
   "method": "add_source"
  },
  {
   "params": {
    "to_port": 100027, 
    "from_port": 150027
   }, 
   "jsonrpc": "2.0", 
   "id": 8, 
   "method": "add_link"
  },
  {
   "params": {
    "hs": {
     "diff": [
      []
     ], 
     "list": [
      "xxxxxxxx,xxxxxxxx,xxxxxxxx,xxxxxxxx,xxxxxxxx,xxxxxxxx"
     ]
    }, 
    "ports": [
     150027
    ]
   }, 
   "jsonrpc": "2.0", 
   "id": 9, 
   "method": "add_source"
  },
  {
   "params": {
    "to_port": 100028, 
    "from_port": 150028
   }, 
   "jsonrpc": "2.0", 
   "id": 8, 
   "method": "add_link"
  },
  {
   "params": {
    "hs": {
     "diff": [
      []
     ], 
     "list": [
      "xxxxxxxx,xxxxxxxx,xxxxxxxx,xxxxxxxx,xxxxxxxx,xxxxxxxx"
     ]
    }, 
    "ports": [
     150028
    ]
   }, 
   "jsonrpc": "2.0", 
   "id": 9, 
   "method": "add_source"
  },
  {
   "params": {
    "to_port": 100030, 
    "from_port": 150030
   }, 
   "jsonrpc": "2.0", 
   "id": 8, 
   "method": "add_link"
  },
  {
   "params": {
    "hs": {
     "diff": [
      []
     ], 
     "list": [
      "xxxxxxxx,xxxxxxxx,xxxxxxxx,xxxxxxxx,xxxxxxxx,xxxxxxxx"
     ]
    }, 
    "ports": [
     150030
    ]
   }, 
   "jsonrpc": "2.0", 
   "id": 9, 
   "method": "add_source"
  },
  {
   "params": {
    "to_port": 100031, 
    "from_port": 150031
   }, 
   "jsonrpc": "2.0", 
   "id": 8, 
   "method": "add_link"
  },
  {
   "params": {
    "hs": {
     "diff": [
      []
     ], 
     "list": [
      "xxxxxxxx,xxxxxxxx,xxxxxxxx,xxxxxxxx,xxxxxxxx,xxxxxxxx"
     ]
    }, 
    "ports": [
     150031
    ]
   }, 
   "jsonrpc": "2.0", 
   "id": 9, 
   "method": "add_source"
  },
  {
   "params": {
    "to_port": 100032, 
    "from_port": 150032
   }, 
   "jsonrpc": "2.0", 
   "id": 8, 
   "method": "add_link"
  },
  {
   "params": {
    "hs": {
     "diff": [
      []
     ], 
     "list": [
      "xxxxxxxx,xxxxxxxx,xxxxxxxx,xxxxxxxx,xxxxxxxx,xxxxxxxx"
     ]
    }, 
    "ports": [
     150032
    ]
   }, 
   "jsonrpc": "2.0", 
   "id": 9, 
   "method": "add_source"
  },
  {
   "params": {
    "to_port": 100033, 
    "from_port": 150033
   }, 
   "jsonrpc": "2.0", 
   "id": 8, 
   "method": "add_link"
  },
  {
   "params": {
    "hs": {
     "diff": [
      []
     ], 
     "list": [
      "xxxxxxxx,xxxxxxxx,xxxxxxxx,xxxxxxxx,xxxxxxxx,xxxxxxxx"
     ]
    }, 
    "ports": [
     150033
    ]
   }, 
   "jsonrpc": "2.0", 
   "id": 9, 
   "method": "add_source"
  }





  // {
  //  "params": {
  //   "to_port": 200047, 
  //   "from_port": 420022
  //  }, 
  //  "jsonrpc": "2.0", 
  //  "id": 2, 
  //  "method": "remove_link"
  // },
  // {
  //  "params": {
  //   "to_port": 200047, 
  //   "from_port": 420022
  //  }, 
  //  "jsonrpc": "2.0", 
  //  "id": 3, 
  //  "method": "add_link"
  // },
  // {
  //  "params": {
  //   "to_port": 400017, 
  //   "from_port": 720014
  //  }, 
  //  "jsonrpc": "2.0", 
  //  "id": 2, 
  //  "method": "remove_link"
  // },
  // {
  //  "params": {
  //   "to_port": 400017, 
  //   "from_port": 720014
  //  }, 
  //  "jsonrpc": "2.0", 
  //  "id": 3, 
  //  "method": "add_link"
  // },
  // {
  //  "params": {
  //   "to_port": 420032, 
  //   "from_port": 300003
  //  }, 
  //  "jsonrpc": "2.0", 
  //  "id": 2, 
  //  "method": "remove_link"
  // },
  // {
  //  "params": {
  //   "to_port": 420032, 
  //   "from_port": 300003
  //  }, 
  //  "jsonrpc": "2.0", 
  //  "id": 3, 
  //  "method": "add_link"
  // },
  // {
  //  "params": {
  //   "to_port": 720015, 
  //   "from_port": 800037
  //  }, 
  //  "jsonrpc": "2.0", 
  //  "id": 2, 
  //  "method": "remove_link"
  // },
  // {
  //  "params": {
  //   "to_port": 720015, 
  //   "from_port": 800037
  //  }, 
  //  "jsonrpc": "2.0", 
  //  "id": 3, 
  //  "method": "add_link"
  // },
  // {
  //  "params": {
  //   "to_port": 500024, 
  //   "from_port": 820008
  //  }, 
  //  "jsonrpc": "2.0", 
  //  "id": 2, 
  //  "method": "remove_link"
  // },
  // {
  //  "params": {
  //   "to_port": 500024, 
  //   "from_port": 820008
  //  }, 
  //  "jsonrpc": "2.0", 
  //  "id": 3, 
  //  "method": "add_link"
  // },
  // {
  //  "params": {
  //   "to_port": 400007, 
  //   "from_port": 320007
  //  }, 
  //  "jsonrpc": "2.0", 
  //  "id": 2, 
  //  "method": "remove_link"
  // },
  // {
  //  "params": {
  //   "to_port": 100018, 
  //   "from_port": 320045
  //  }, 
  //  "jsonrpc": "2.0", 
  //  "id": 3, 
  //  "method": "add_link"
  // },
  // {
  //  "params": {
  //   "to_port": 900015, 
  //   "from_port": 120030
  //  }, 
  //  "jsonrpc": "2.0", 
  //  "id": 2, 
  //  "method": "remove_link"
  // },
  // {
  //  "params": {
  //   "to_port": 900015, 
  //   "from_port": 120030
  //  }, 
  //  "jsonrpc": "2.0", 
  //  "id": 3, 
  //  "method": "add_link"
  // }

 ]
}